bolero_process/__init__.py
bolero_process/atac/__init__.py
bolero_process/atac/bulk/Snakefile.smk
bolero_process/atac/bulk/__init__.py
bolero_process/atac/bulk/bulk.py
bolero_process/atac/pseudobulk/pseudo_bulk.py
bolero_process/atac/pseudobulk/split_to_pseudobulk.py
bolero_process/atac/sc/__init__.py
bolero_process/atac/sc/fragments_to_zarr.py
bolero_process/atac/sc/zarr_io.py
bolero_process/atac/scprinter/preprocess.smk
bolero_process/sky/__init__.py
bolero_process/sky/template/sky_mapping.yaml
bolero_process-0.0.20.dist-info/METADATA
bolero_process-0.0.20.dist-info/WHEEL
bolero_process-0.0.20.dist-info/licenses/LICENSE
bolero_process-0.0.20.dist-info/RECORD
