Metadata-Version: 2.3
Name: bolero-process
Version: 0.0.20
Summary: Data preprocessing for bolero package
Project-URL: Documentation, https://bolero-process.readthedocs.io/
Project-URL: Source, https://github.com/lhqing/bolero-process
Project-URL: Home-page, https://github.com/lhqing/bolero-process
Author: Hanqing Liu
Maintainer-email: Hanqing Liu <hanqingliu@fas.harvard.edu>
License: MIT License
License-File: LICENSE
Requires-Python: >=3.6
Requires-Dist: anndata
Requires-Dist: joblib
Requires-Dist: numba
Requires-Dist: numpy
Requires-Dist: pandas
Requires-Dist: pybigwig
Requires-Dist: pyranges
Requires-Dist: scipy
Requires-Dist: session-info
Requires-Dist: tqdm
Requires-Dist: xarray
Requires-Dist: zarr
Provides-Extra: dev
Requires-Dist: pre-commit; extra == 'dev'
Requires-Dist: twine>=4.0.2; extra == 'dev'
Provides-Extra: doc
Requires-Dist: docutils!=0.18.*,!=0.19.*,>=0.8; extra == 'doc'
Requires-Dist: ghp-import; extra == 'doc'
Requires-Dist: ipykernel; extra == 'doc'
Requires-Dist: ipython; extra == 'doc'
Requires-Dist: jupyter-book; extra == 'doc'
Requires-Dist: myst-nb; extra == 'doc'
Requires-Dist: pandas; extra == 'doc'
Requires-Dist: sphinx-autodoc-typehints; extra == 'doc'
Requires-Dist: sphinx-book-theme>=1.0.0; extra == 'doc'
Requires-Dist: sphinx-copybutton; extra == 'doc'
Requires-Dist: sphinx>=4; extra == 'doc'
Requires-Dist: sphinxcontrib-bibtex>=1.0.0; extra == 'doc'
Requires-Dist: sphinxext-opengraph; extra == 'doc'
Provides-Extra: test
Requires-Dist: coverage; extra == 'test'
Requires-Dist: pytest; extra == 'test'
